{
  "branches": 7,
  "total_samples": 201221,
  "by_branch": {
    "yw_fm_ad3_d1_9": {
      "cutoff": 589.0,
      "overdue_rate": 0.0215,
      "total": 11180,
      "pass": 559,
      "info": "еЉВзљС-е•≥-еєійЊДвЙ§3-йЗСйҐЭвЙ§2"
    },
    "yw_fm_ad3_g1_10": {
      "cutoff": 576.0,
      "overdue_rate": 0.028,
      "total": 4290,
      "pass": 214,
      "info": "еЉВзљС-е•≥-еєійЊДвЙ§3-йЗСйҐЭ>2"
    },
    "yw_fm_ag3_11": {
      "cutoff": 591.0,
      "overdue_rate": 0.0216,
      "total": 37980,
      "pass": 1899,
      "info": "еЉВзљС-е•≥-еєійЊД>3"
    },
    "yw_m_ad3_d1_12": {
      "cutoff": 537.0,
      "overdue_rate": 0.0883,
      "total": 20385,
      "pass": 1019,
      "info": "еЉВзљС-зФЈ-еєійЊДвЙ§4(зїЖеИЖвЙ§2)"
    },
    "yw_m_ad3_d1_13": {
      "cutoff": 541.0,
      "overdue_rate": 0.0642,
      "total": 43630,
      "pass": 2181,
      "info": "еЉВзљС-зФЈ-еєійЊДвЙ§4(зїЖеИЖ>2)"
    },
    "yw_m_ag3_d15_14": {
      "cutoff": 569.0,
      "overdue_rate": 0.0539,
      "total": 70106,
      "pass": 3505,
      "info": "еЉВзљС-зФЈ-еєійЊД>4-йЗСйҐЭвЙ§3"
    },
    "yw_m_ag3_g15_15": {
      "cutoff": 551.0,
      "overdue_rate": 0.0455,
      "total": 13650,
      "pass": 682,
      "info": "еЉВзљС-зФЈ-еєійЊД>4-йЗСйҐЭ>3"
    }
  }
}